{
  "uuid": "c6b715b4",
  "name": "Ch 1",
  "opacity": 1.0,
  "blend_mode": "normal",
  "decks": [
    {
      "uuid": "17af0bbc",
      "name": "quantum_membrane",
      "source": {
        "type": "Shader",
        "path": "shaders/quantum_membrane.fs",
        "params": {
          "zoom": 0.5,
          "color_glow": [
            0.26191065,
            0.26191065,
            0.26191065,
            1.0
          ],
          "color_b": [
            0.5466488,
            0.5466488,
            0.5466488,
            1.0
          ],
          "cam_x": 0.0,
          "bg_color": [
            0.0,
            0.0,
            0.0,
            1.0
          ],
          "membrane_amp": 1.55,
          "fly_speed": 0.25,
          "wave_speed": 0.0,
          "glow_intensity": 1.0,
          "glow_radius": 0.08,
          "grid_thickness": 0.03,
          "cam_y": 0.4,
          "membrane_freq": 2.0,
          "grid_density": 18.0,
          "spin_x": 0.0,
          "spin_y": 0.1,
          "color_a": [
            1.0,
            1.0,
            1.0,
            1.0
          ]
        }
      },
      "effects": [
        {
          "uuid": "88ce255c",
          "path": "shaders/edge_detect.fs",
          "enabled": true,
          "params": {
            "sensitivity": 0.9,
            "edge_color": [
              1.0,
              1.0,
              1.0,
              1.0
            ],
            "use_source_color": 0.0,
            "bg_opacity": 0.0
          }
        }
      ],
      "opacity": 1.0,
      "blend_mode": "normal",
      "mute": false,
      "solo": false,
      "z_index": 0,
      "modulation": [
        {
          "source_uuid": "8bab563e",
          "source": {
            "AudioBand": {
              "source_id": null,
              "freq_low": 20.0,
              "freq_high": 110.0,
              "gain": 1.0,
              "smoothing": 0.95,
              "mode": "Direct",
              "noise_gate": 0.1
            }
          },
          "assignments": [
            {
              "param": "membrane_amp",
              "amount": 0.5
            }
          ]
        }
      ]
    },
    {
      "uuid": "8cfbeccb",
      "name": "lagrangian",
      "source": {
        "type": "Shader",
        "path": "/Users/206653756/projects/vj/shaders/lagrangian.fs",
        "params": {
          "depth_layers": 5.0,
          "h_position": 0.95,
          "speed": 4.5,
          "rotation": 0.0,
          "bg_color": [
            0.0,
            0.0,
            0.0,
            0.0
          ],
          "fg_color": [
            1.0,
            1.0,
            1.0,
            1.0
          ],
          "text_size": 0.065,
          "spread": 1.0,
          "glow": 1.0
        }
      },
      "effects": [],
      "opacity": 1.0,
      "blend_mode": "normal",
      "mute": false,
      "solo": false,
      "z_index": 0
    },
    {
      "uuid": "659b4a6e",
      "name": "lagrangian",
      "source": {
        "type": "Shader",
        "path": "shaders/lagrangian.fs",
        "params": {
          "rotation": 0.2,
          "speed": 9.0,
          "glow": 0.5,
          "text_size": 0.06,
          "h_position": 1.0,
          "spread": 0.25,
          "fg_color": [
            1.0,
            1.0,
            1.0,
            1.0
          ],
          "bg_color": [
            0.0,
            0.0,
            0.0,
            0.0
          ],
          "depth_layers": 4.7
        }
      },
      "effects": [],
      "opacity": 1.0,
      "blend_mode": "normal",
      "mute": false,
      "solo": false,
      "z_index": 0
    }
  ],
  "effects": [
    {
      "uuid": "696d4521",
      "path": "shaders/vhs_crt.fs",
      "enabled": true,
      "params": {
        "distortion": 0.02,
        "noise_amount": 0.07,
        "color_bleed": 0.0055,
        "tracking_error": 0.17,
        "vignette_amount": 0.0,
        "scanline_strength": 0.53
      }
    }
  ]
}